petstore_gaurav_test1_ti_client/__init__.py
petstore_gaurav_test1_ti_client/api_client.py
petstore_gaurav_test1_ti_client/api_response.py
petstore_gaurav_test1_ti_client/configuration.py
petstore_gaurav_test1_ti_client/exceptions.py
petstore_gaurav_test1_ti_client/py.typed
petstore_gaurav_test1_ti_client/rest.py
petstore_gaurav_test1_ti_client/api/__init__.py
petstore_gaurav_test1_ti_client/api/pet_api.py
petstore_gaurav_test1_ti_client/api/store_api.py
petstore_gaurav_test1_ti_client/api/user_api.py
petstore_gaurav_test1_ti_client/models/__init__.py
petstore_gaurav_test1_ti_client/models/address.py
petstore_gaurav_test1_ti_client/models/api_response.py
petstore_gaurav_test1_ti_client/models/category.py
petstore_gaurav_test1_ti_client/models/customer.py
petstore_gaurav_test1_ti_client/models/order.py
petstore_gaurav_test1_ti_client/models/pet.py
petstore_gaurav_test1_ti_client/models/tag.py
petstore_gaurav_test1_ti_client/models/user.py
petstore_gaurav_test1_ti_client-1.0.0.dist-info/METADATA
petstore_gaurav_test1_ti_client-1.0.0.dist-info/WHEEL
petstore_gaurav_test1_ti_client-1.0.0.dist-info/top_level.txt
petstore_gaurav_test1_ti_client-1.0.0.dist-info/RECORD
